{
  "updatedAt": "2025-11-11T06:56:31.100Z",
  "top": [
    {
      "source": "BBC World",
      "title": "At least eight killed after car explodes near Delhi's Red Fort",
      "url": "https://www.bbc.com/news/articles/ceq0p8qnnrno?at_medium=RSS&at_campaign=rss",
      "summary": "Twenty more were injured in the blast, the cause of which is still unknown, authorities say."
    },
    {
      "source": "BBC World",
      "title": "US Senate to debate deal to end longest shutdown after overnight breakthrough",
      "url": "https://www.bbc.com/news/articles/cpd2p2eddnzo?at_medium=RSS&at_campaign=rss",
      "summary": "The measure signals a major breakthrough but the deal still needs to get over more hurdles in Congress. "
    },
    {
      "source": "BBC World",
      "title": "Syria to join US-led coalition to defeat IS group after Trump meeting",
      "url": "https://www.bbc.com/news/articles/cvgvz6316zwo?at_medium=RSS&at_campaign=rss",
      "summary": "Ahmed al-Sharaa, once branded a terrorist by the US, became the first Syrian leader to visit the White House. "
    },
    {
      "source": "BBC Technology",
      "title": "Cryptoqueen who fled China for London mansion to be sentenced over £5bn Bitcoin stash",
      "url": "https://www.bbc.com/news/articles/cvg4w1g9ezko?at_medium=RSS&at_campaign=rss",
      "summary": "Qian Zhimin bought cryptocurrency using funds stolen from thousands of Chinese pensioners, say police.\n"
    },
    {
      "source": "BBC Technology",
      "title": "Battle over Chinese chip maker rocks global car industry",
      "url": "https://www.bbc.com/news/articles/cr43kyn9d6po?at_medium=RSS&at_campaign=rss",
      "summary": "In an extraordinary move, the Dutch government seized control of Nexperia, triggering anger in Beijing."
    },
    {
      "source": "BBC Technology",
      "title": "A jailed hacking kingpin reveals all about the gang that left a trail of destruction",
      "url": "https://www.bbc.com/news/articles/cm2w0pvg4wko?at_medium=RSS&at_campaign=rss",
      "summary": "One of the world's most prominent cyber-criminals speaks to the BBC in an exclusive interview."
    },
    {
      "source": "The Verge",
      "title": {
        "#text": "Siri Shortcuts now works with Samsung SmartThings routines",
        "@_type": "html"
      },
      "url": "https://www.theverge.com/news/818054/samsung-smartthings-routines-siri-ios-support",
      "summary": "(要約準備中)"
    },
    {
      "source": "The Verge",
      "title": {
        "#text": "The best early Black Friday deals we’ve found so far on laptops, TVs, and more",
        "@_type": "html"
      },
      "url": "https://www.theverge.com/tech/814345/black-friday-best-early-deals-2025",
      "summary": "(要約準備中)"
    },
    {
      "source": "The Verge",
      "title": {
        "#text": "Paramount Plus is getting a price hike in early 2026",
        "@_type": "html"
      },
      "url": "https://www.theverge.com/news/818019/paramount-plus-price-increase-us-2026",
      "summary": "(要約準備中)"
    }
  ]
}