{
  "updatedAt": "2026-02-18T07:16:47.851Z",
  "top": [
    {
      "source": "BBC World",
      "title": "I would scream in my sleep: Women from Syria's Alawite minority tell of kidnap and rape",
      "url": "https://www.bbc.com/news/articles/cn5g751pl7lo?at_medium=RSS&at_campaign=rss",
      "summary": "The BBC hears harrowing accounts of assaults appearing to target the sect of former President Assad."
    },
    {
      "source": "BBC World",
      "title": "Witkoff says 'meaningful progress' made as Ukraine talks enter second day",
      "url": "https://www.bbc.com/news/articles/cgk2mlv2k1ro?at_medium=RSS&at_campaign=rss",
      "summary": "The US special envoy struck an optimistic note after the first day of talks in Geneva, but hopes for a breakthrough remain low. "
    },
    {
      "source": "BBC World",
      "title": "Rescuers search for 10 missing skiers after California avalanche",
      "url": "https://www.bbc.com/news/articles/c62dke15357o?at_medium=RSS&at_campaign=rss",
      "summary": "Rescuers are racing to the scene, which has seen about 30 inches (76cm) of snowfall in the last 24 hours."
    },
    {
      "source": "BBC Technology",
      "title": "'I do not trust them' - top streamers left concerned by Discord age checks",
      "url": "https://www.bbc.com/news/articles/cn4g8ynpwl8o?at_medium=RSS&at_campaign=rss",
      "summary": "The platform's plan to roll out global age checks has caused concern in streaming communities."
    },
    {
      "source": "BBC Technology",
      "title": "How dark web agent spotted bedroom wall clue to rescue girl from years of harm",
      "url": "https://www.bbc.com/news/articles/cx2gn239exlo?at_medium=RSS&at_campaign=rss",
      "summary": "Detectives desperate to locate a 12-year-old, seen abused online, found a surprising lead.\n"
    },
    {
      "source": "BBC Technology",
      "title": "Could Bill Gates and political tussles overshadow AI safety debate in Delhi?",
      "url": "https://www.bbc.com/news/articles/cr5l6gnen72o?at_medium=RSS&at_campaign=rss",
      "summary": "As global tech leaders meet Delhi, India hopes to level the playing field for countries outside the US and China."
    },
    {
      "source": "The Verge",
      "title": {
        "#text": "Meta&#8217;s new deal with Nvidia buys up millions of AI chips",
        "@_type": "html"
      },
      "url": "https://www.theverge.com/ai-artificial-intelligence/880513/nvidia-meta-ai-grace-vera-chips",
      "summary": "(要約準備中)"
    },
    {
      "source": "The Verge",
      "title": {
        "#text": "Stephen Colbert says CBS banned him from airing this James Talarico interview",
        "@_type": "html"
      },
      "url": "https://www.theverge.com/policy/880009/stephen-colbert-cbs-fcc-brendan-carr-talarico-interview",
      "summary": "(要約準備中)"
    },
    {
      "source": "The Verge",
      "title": {
        "#text": "The best deals on MacBooks right now",
        "@_type": "html"
      },
      "url": "https://www.theverge.com/22399419/apple-macbook-air-pro-mac-mini-imac-deals",
      "summary": "(要約準備中)"
    }
  ]
}