{
  "updatedAt": "2025-11-14T06:56:05.182Z",
  "top": [
    {
      "source": "BBC World",
      "title": "Epstein email says Andrew had photo taken with Virginia Giuffre",
      "url": "https://www.bbc.com/news/articles/cglgj08erywo?at_medium=RSS&at_campaign=rss",
      "summary": "The message sent by Epstein reads: \"Yes she [Giuffre] was on my plane and yes she had her picture taken with Andrew\""
    },
    {
      "source": "BBC World",
      "title": "What we know about new Epstein emails that mention Trump",
      "url": "https://www.bbc.com/news/articles/c3rj0d97ynvo?at_medium=RSS&at_campaign=rss",
      "summary": "In emails released by Democrats, Epstein says Trump \"knew about the girls\". The White House says they are an attempt to \"smear\" the president."
    },
    {
      "source": "BBC World",
      "title": "Germany agrees new military service plan to boost troop numbers",
      "url": "https://www.bbc.com/news/articles/c4gpkerdn9qo?at_medium=RSS&at_campaign=rss",
      "summary": "The new military service plan will mandate all 18-year-old men to fill out a questionnaire on their suitability to serve. "
    },
    {
      "source": "BBC Technology",
      "title": "PC gaming giant Valve unveils new console to rival Xbox and PlayStation",
      "url": "https://www.bbc.com/news/articles/cd679n9lnx5o?at_medium=RSS&at_campaign=rss",
      "summary": "The Steam Machine is a console designed to allow gamers to play PC games on their TV."
    },
    {
      "source": "BBC Technology",
      "title": "£220 'for a cut-up sock' - Apple's new iPhone Pocket ridiculed online",
      "url": "https://www.bbc.com/news/articles/cn97ndgpnq7o?at_medium=RSS&at_campaign=rss",
      "summary": "Many took aim at the high price online, while others made fun of its striking likeness to a piece of footwear."
    },
    {
      "source": "BBC Technology",
      "title": "Danish man given suspended sentence for sharing nude film scenes on Reddit",
      "url": "https://www.bbc.com/news/articles/c201yq43k66o?at_medium=RSS&at_campaign=rss",
      "summary": "Police said the man shared 347 clips of naked actors on the social media site, which were viewed 4.2 million times."
    },
    {
      "source": "The Verge",
      "title": {
        "#text": "What insiders anonymously think about the AI race",
        "@_type": "html"
      },
      "url": "https://www.theverge.com/column/820664/cerebral-valley-conference-ai-anonymous-survey",
      "summary": "(要約準備中)"
    },
    {
      "source": "The Verge",
      "title": {
        "#text": "The best instant cameras you can buy right now",
        "@_type": "html"
      },
      "url": "https://www.theverge.com/23133103/best-instant-cameras-fujifilm-polaroid-kodak",
      "summary": "(要約準備中)"
    },
    {
      "source": "The Verge",
      "title": {
        "#text": "Apple TV is getting MLS games at no extra cost",
        "@_type": "html"
      },
      "url": "https://www.theverge.com/news/820595/apple-tv-mls-games-bundle-no-extra-cost-subscription-season-pass",
      "summary": "(要約準備中)"
    }
  ]
}